rtl/consts/Consts.v
// 寄存器位宽
`define REG_SEL 5
// 寄存器数量
`define REG_NUM 32

// 指令类型相关常量
`define IMM_TYPE_WIDTH 2
`define IMM_I `IMM_TYPE_WIDTH'd0
`define IMM_S `IMM_TYPE_WIDTH'd1
`define IMM_U `IMM_TYPE_WIDTH'd2
`define IMM_J `IMM_TYPE_WIDTH'd3

//Important Wire
`define DATA_LEN 32
`define INSN_LEN 32
`define ADDR_LEN 32
`define ISSUE_NUM 2
`define ENTRY_POINT `ADDR_LEN'h0

//Decoder
`define RS_ENT_SEL 3
`define RS_ENT_ALU 1
`define RS_ENT_BRANCH 2
`define RS_ENT_JAL `RS_ENT_BRANCH
`define RS_ENT_JALR `RS_ENT_BRANCH
`define RS_ENT_MUL 3
`define RS_ENT_DIV 3
`define RS_ENT_LDST 4

// 保留站相关
`define ALU_ENT_SEL 3
`define ALU_ENT_NUM 8
`define BRANCH_ENT_SEL 2
`define BRANCH_ENT_NUM 4
`define LDST_ENT_SEL 2
`define LDST_ENT_NUM 4
`define MUL_ENT_SEL 1
`define MUL_ENT_NUM 2

// Store Buffer 相关
`define STBUF_ENT_SEL 5
`define STBUF_ENT_NUM 32

// BTB 相关
`define BTB_IDX_SEL 9
`define BTB_IDX_NUM 512
`define BTB_TAG_LEN 20

// Gshare 相关
`define GSH_BHR_LEN 10
`define GSH_PHT_SEL 10
`define GSH_PHT_NUM 1024

// TagGenerator 相关
`define SPECTAG_LEN 5
`define BRDEPTH_LEN 5

// ROB 相关
`define ROB_SEL 6
`define ROB_NUM 64
`define RRF_SEL `ROB_SEL
`define RRF_NUM `ROB_NUM


`define SRC_A_SEL_WIDTH 2
`define SRC_A_RS1  `SRC_A_SEL_WIDTH'd0
`define SRC_A_PC   `SRC_A_SEL_WIDTH'd1
`define SRC_A_ZERO `SRC_A_SEL_WIDTH'd2


`define SRC_B_SEL_WIDTH 2
`define SRC_B_RS2  `SRC_B_SEL_WIDTH'd0
`define SRC_B_IMM  `SRC_B_SEL_WIDTH'd1
`define SRC_B_FOUR `SRC_B_SEL_WIDTH'd2
`define SRC_B_ZERO `SRC_B_SEL_WIDTH'd3

`define MEM_TYPE_WIDTH 3
`define MEM_TYPE_LB  `MEM_TYPE_WIDTH'd0
`define MEM_TYPE_LH  `MEM_TYPE_WIDTH'd1
`define MEM_TYPE_LW  `MEM_TYPE_WIDTH'd2
`define MEM_TYPE_LD  `MEM_TYPE_WIDTH'd3
`define MEM_TYPE_LBU `MEM_TYPE_WIDTH'd4
`define MEM_TYPE_LHU `MEM_TYPE_WIDTH'd5
`define MEM_TYPE_LWU `MEM_TYPE_WIDTH'd6

`define MEM_TYPE_SB  `MEM_TYPE_WIDTH'd0
`define MEM_TYPE_SH  `MEM_TYPE_WIDTH'd1
`define MEM_TYPE_SW  `MEM_TYPE_WIDTH'd2
`define MEM_TYPE_SD  `MEM_TYPE_WIDTH'd3

`define MD_OP_WIDTH 2
`define MD_OP_MUL `MD_OP_WIDTH'd0
`define MD_OP_DIV `MD_OP_WIDTH'd1
`define MD_OP_REM `MD_OP_WIDTH'd2

`define MD_OUT_SEL_WIDTH 2
`define MD_OUT_LO  `MD_OUT_SEL_WIDTH'd0
`define MD_OUT_HI  `MD_OUT_SEL_WIDTH'd1
`define MD_OUT_REM `MD_OUT_SEL_WIDTH'd2

rtl/core/ROB.v
// `include "consts/Consts.v"
module ROB (
    input wire clk,
    input wire reset,

    input wire dp1_i,                                               //是否发射
    input wire [`ROB_SEL-1:0] dp1_addr_i,                           //第一条发射的指令在ROB的地址
    // input wire [`ROB_SEL-1:0] dispatch_ptr_i,
    // input wire [`INSN_LEN-1:0] pc_dp1_i,
    input wire finish_ex_alu1_i,                                    //alu1单元是否执行完成
    input wire [`RRF_SEL-1:0] ex_alu1_addr_i,                       //alu1执行完成的指令在ROB的地址

    input wire [`REG_SEL-1:0] dst_dp1_i,
    input wire isValid_dst_dp1_i,

    output reg [`ROB_SEL-1:0] commit_ptr_o,
    output reg   arfwe_1_o,
    output reg [`REG_SEL-1:0] dst_arf_1_o



);
    reg [`ROB_NUM-1:0] finish;
    reg [`REG_SEL-1:0] dst [0:`ROB_NUM-1];                         //储存目的逻辑寄存器的编号
    reg [`ROB_NUM-1:0] isValid_dst;                                


    wire commit_1 = finish[commit_ptr_o];

    assign dst_arf_1_o = dst[commit_ptr_o];
    assign arfwe_1_o =  isValid_dst[commit_ptr_o] & commit_1;
    

    always @(posedge clk ) begin
        if(reset) begin
            commit_ptr_o <= 0;
            finish <= 0;
        end
        else begin
            commit_ptr_o <= (commit_ptr_o + commit_1) % (`ROB_NUM);
            if(finish_ex_alu1_i)
                finish[ex_alu1_addr_i] <= 1'b1;

        end
    end


    always @(posedge clk ) begin
        if(dp1_i) begin
            finish[dp1_addr_i] <= 1'b0;
            dst[dp1_addr_i] <= dst_dp1_i;
            isValid_dst[dp1_addr_i] <= isValid_dst_dp1_i;
        end
    end



endmodule

testbench/ROB_tb.v
`include "../rtl/consts/Consts.v"
module ROB_tb();
    reg clk;
    reg reset;
    reg dp1_i;
    reg [`ROB_SEL-1:0] dp1_addr_i;
    reg finish_ex_alu1_i;
    reg [`RRF_SEL-1:0] ex_alu1_addr_i;
    reg [`REG_SEL-1:0] dst_dp1_i;
    reg isValid_dst_dp1_i;

    wire [`ROB_SEL-1:0] commit_ptr_o;
    wire arfwe_1_o;
    wire [`REG_SEL-1:0] dst_arf_1_o;

    // 实例化ROB
    ROB dut (
        .clk(clk),
        .reset(reset),
        .dp1_i(dp1_i),
        .dp1_addr_i(dp1_addr_i),
        .finish_ex_alu1_i(finish_ex_alu1_i),
        .ex_alu1_addr_i(ex_alu1_addr_i),
        .dst_dp1_i(dst_dp1_i),
        .isValid_dst_dp1_i(isValid_dst_dp1_i),
        .commit_ptr_o(commit_ptr_o),
        .arfwe_1_o(arfwe_1_o),
        .dst_arf_1_o(dst_arf_1_o)
    );

    initial begin
        clk = 0;
        forever #5 clk = ~clk;
    end

    initial begin
                $dumpfile("ROB_tb.vcd");    //生成的vcd文件名称
                $dumpvars(0, ROB_tb);       //要记录的信号  0代表所有
            end
 
    initial begin
        reset = 1;
        dp1_i = 0;
        dp1_addr_i = 0;
        finish_ex_alu1_i = 0;
        ex_alu1_addr_i = 0;
        dst_dp1_i = 0;
        isValid_dst_dp1_i = 0;

        #10 reset = 0; 


        #20 dp1_i = 1;
        #5 dp1_addr_i = 3;
        #5 finish_ex_alu1_i = 1;
        #5 ex_alu1_addr_i = 3;
        #5 dst_dp1_i = 5;
        #5 isValid_dst_dp1_i = 1;


        #20 dp1_i = 1;
        #5 dp1_addr_i = 4;
        #5 finish_ex_alu1_i = 1;
        #5 ex_alu1_addr_i = 4;
        #5 dst_dp1_i = 6;
        #5 isValid_dst_dp1_i = 1;

 

        #100 $stop;
  end

endmodule

testbench/ROB_tb.vcd
$date
	Sat Dec  2 14:41:40 2023
$end
$version
	Icarus Verilog
$end
$timescale
	1s
$end
$scope module ROB_tb $end
$var wire 5 ! dst_arf_1_o [4:0] $end
$var wire 6 " commit_ptr_o [5:0] $end
$var wire 1 # arfwe_1_o $end
$var reg 1 $ clk $end
$var reg 6 % dp1_addr_i [5:0] $end
$var reg 1 & dp1_i $end
$var reg 5 ' dst_dp1_i [4:0] $end
$var reg 6 ( ex_alu1_addr_i [5:0] $end
$var reg 1 ) finish_ex_alu1_i $end
$var reg 1 * isValid_dst_dp1_i $end
$var reg 1 + reset $end
$scope module dut $end
$var wire 1 # arfwe_1_o $end
$var wire 1 $ clk $end
$var wire 6 , dp1_addr_i [5:0] $end
$var wire 1 & dp1_i $end
$var wire 5 - dst_arf_1_o [4:0] $end
$var wire 5 . dst_dp1_i [4:0] $end
$var wire 6 / ex_alu1_addr_i [5:0] $end
$var wire 1 ) finish_ex_alu1_i $end
$var wire 1 * isValid_dst_dp1_i $end
$var wire 1 + reset $end
$var wire 1 0 commit_1 $end
$var reg 6 1 commit_ptr_o [5:0] $end
$var reg 64 2 finish [63:0] $end
$var reg 64 3 isValid_dst [63:0] $end
$upscope $end
$upscope $end
$enddefinitions $end
$comment Show the parameter values. $end
$dumpall
$end
#0
$dumpvars
bx 3
bx 2
bx 1
x0
b0 /
b0 .
bx -
b0 ,
1+
0*
0)
b0 (
b0 '
0&
b0 %
0$
x#
bx "
bx !
$end
#5
0#
00
b0 2
b0 "
b0 1
1$
#10
0$
0+
#15
1$
#20
0$
#25
1$
#30
0$
1&
#35
bx0xxx 3
1$
b11 %
b11 ,
#40
0$
1)
#45
b1000 2
1$
b11 (
b11 /
#50
0$
b101 '
b101 .
#55
bx1xxx 3
b0 2
1$
1*
#60
0$
#65
b1000 2
1$
#70
0$
#75
b0 2
1$
#80
0$
b100 %
b100 ,
#85
b1000 2
bx11xxx 3
1$
#90
0$
b100 (
b100 /
#95
b1000 2
1$
b110 '
b110 .
#100
0$
#105
b11000 2
1$
#110
0$
#115
b1000 2
1$
#120
0$
#125
b11000 2
1$
#130
0$
#135
b1000 2
1$
#140
0$
#145
b11000 2
1$
#150
0$
#155
b1000 2
1$
#160
0$
#165
b11000 2
1$
#170
0$
#175
b1000 2
1$
#180
0$
#185
b11000 2
1$
#190
0$
#195
b1000 2
1$
