rtl/consts/Consts.v
// 寄存器位宽
`define REG_SEL 5
// 寄存器数量
`define REG_NUM 32

// 指令类型相关常量
`define IMM_TYPE_WIDTH 2
`define IMM_I `IMM_TYPE_WIDTH'd0
`define IMM_S `IMM_TYPE_WIDTH'd1
`define IMM_U `IMM_TYPE_WIDTH'd2
`define IMM_J `IMM_TYPE_WIDTH'd3

//Important Wire
`define DATA_LEN 32
`define INSN_LEN 32
`define ADDR_LEN 32
`define ISSUE_NUM 2
`define ENTRY_POINT `ADDR_LEN'h0

//Decoder
`define RS_ENT_SEL 3
`define RS_ENT_ALU 1
`define RS_ENT_BRANCH 2
`define RS_ENT_JAL `RS_ENT_BRANCH
`define RS_ENT_JALR `RS_ENT_BRANCH
`define RS_ENT_MUL 3
`define RS_ENT_DIV 3
`define RS_ENT_LDST 4

// 保留站相关
`define ALU_ENT_SEL 3
`define ALU_ENT_NUM 8
`define BRANCH_ENT_SEL 2
`define BRANCH_ENT_NUM 4
`define LDST_ENT_SEL 2
`define LDST_ENT_NUM 4
`define MUL_ENT_SEL 1
`define MUL_ENT_NUM 2

// Store Buffer 相关
`define STBUF_ENT_SEL 5
`define STBUF_ENT_NUM 32

// BTB 相关
`define BTB_IDX_SEL 9
`define BTB_IDX_NUM 512
`define BTB_TAG_LEN 20

// Gshare 相关
`define GSH_BHR_LEN 10
`define GSH_PHT_SEL 10
`define GSH_PHT_NUM 1024

// TagGenerator 相关
`define SPECTAG_LEN 5
`define BRDEPTH_LEN 5

// ROB 相关
`define ROB_SEL 6
`define ROB_NUM 64
`define RRF_SEL `ROB_SEL
`define RRF_NUM `ROB_NUM


`define SRC_A_SEL_WIDTH 2
`define SRC_A_RS1  `SRC_A_SEL_WIDTH'd0
`define SRC_A_PC   `SRC_A_SEL_WIDTH'd1
`define SRC_A_ZERO `SRC_A_SEL_WIDTH'd2


`define SRC_B_SEL_WIDTH 2
`define SRC_B_RS2  `SRC_B_SEL_WIDTH'd0
`define SRC_B_IMM  `SRC_B_SEL_WIDTH'd1
`define SRC_B_FOUR `SRC_B_SEL_WIDTH'd2
`define SRC_B_ZERO `SRC_B_SEL_WIDTH'd3

`define MEM_TYPE_WIDTH 3
`define MEM_TYPE_LB  `MEM_TYPE_WIDTH'd0
`define MEM_TYPE_LH  `MEM_TYPE_WIDTH'd1
`define MEM_TYPE_LW  `MEM_TYPE_WIDTH'd2
`define MEM_TYPE_LD  `MEM_TYPE_WIDTH'd3
`define MEM_TYPE_LBU `MEM_TYPE_WIDTH'd4
`define MEM_TYPE_LHU `MEM_TYPE_WIDTH'd5
`define MEM_TYPE_LWU `MEM_TYPE_WIDTH'd6

`define MEM_TYPE_SB  `MEM_TYPE_WIDTH'd0
`define MEM_TYPE_SH  `MEM_TYPE_WIDTH'd1
`define MEM_TYPE_SW  `MEM_TYPE_WIDTH'd2
`define MEM_TYPE_SD  `MEM_TYPE_WIDTH'd3

`define MD_OP_WIDTH 2
`define MD_OP_MUL `MD_OP_WIDTH'd0
`define MD_OP_DIV `MD_OP_WIDTH'd1
`define MD_OP_REM `MD_OP_WIDTH'd2

`define MD_OUT_SEL_WIDTH 2
`define MD_OUT_LO  `MD_OUT_SEL_WIDTH'd0
`define MD_OUT_HI  `MD_OUT_SEL_WIDTH'd1
`define MD_OUT_REM `MD_OUT_SEL_WIDTH'd2

rtl/core/ROB.v
// `include "consts/Consts.v"
module ROB (
    input wire clk,
    input wire reset,

    input wire 			  dp1_i,                                     //是否发射
    input wire [`RRF_SEL-1:0] 	  dp1_addr_i,                        //第一条发射的指令在ROB的地址
    input wire [`INSN_LEN-1:0] 	  pc_dp1_i,
    input wire 			  storebit_dp1_i,
    input wire 			  dstvalid_dp1_i,
    input wire [`REG_SEL-1:0] 	  dst_dp1_i,
    input wire [`GSH_BHR_LEN-1:0]  bhr_dp1_i,
    input wire 			  isbranch_dp1_i,
    input wire 			  dp2_i,
    input wire [`RRF_SEL-1:0] 	  dp2_addr_i,
    input wire [`INSN_LEN-1:0] 	  pc_dp2_i,
    input wire 			  storebit_dp2_i,
    input wire 			  dstvalid_dp2_i,
    input wire [`REG_SEL-1:0] 	  dst_dp2_i,
    input wire [`GSH_BHR_LEN-1:0]  bhr_dp2_i,
    input wire 			  isbranch_dp2_i,

    input wire finish_ex_alu1_i,                                    //alu1单元是否执行完成
    input wire [`RRF_SEL-1:0] finish_ex_alu1_addr_i,                       //alu1执行完成的指令在ROB的地址
    input wire 			  finish_ex_alu2_i,
    input wire [`RRF_SEL-1:0] 	  finish_ex_alu2_addr_i,
    input wire 			  finish_ex_mul_i,
    input wire [`RRF_SEL-1:0] 	  finish_exfin_mul_addr_i,
    input wire 			  finish_ex_ldst_i,
    input wire [`RRF_SEL-1:0] 	  finish_ex_ldst_addr_i,
    input wire 			  finish_ex_branch_i,
    input wire [`RRF_SEL-1:0] 	  finish_ex_branch_addr_i,
    input wire 			  finish_ex_branch_brcond_i,
    input wire [`ADDR_LEN-1:0] 	  finish_ex_branch_jmpaddr_i,

    input wire [`RRF_SEL-1:0] dispatch_ptr_i,
    input wire [`RRF_SEL-1:0] rrf_freenum_i,
    input wire prmiss_i,

    output reg [`ROB_SEL-1:0] commit_ptr_1_o,
    output wire [`ROB_SEL-1:0] commit_ptr_2_o,
    output wire[1:0]    comnum_o,
    output wire store_commit_o,
    output wire   arfwe_1_o,
    output wire   arfwe_2_o,
    output wire [`REG_SEL-1:0] dst_arf_1_o,
    output wire [`REG_SEL-1:0] dst_arf_2_o,

    output wire [`ADDR_LEN-1:0] pc_combranch_o,
    output wire [`GSH_BHR_LEN-1:0] bhr_combranch_o 
    output wire [`ADDR_LEN-1:0] jmpaddr_combranch_o,
    output wire brcond_combranch_o,
    output wire combranch_o,
        
    
);
    //表示该 ROB entry 当前是否有效,即是否已被分配给某条指令。当新指令被分派时,会将对应 entry 的 valid 位置1,表示现在有效。
    reg [`ROB_NUM-1:0] valid;
    //表示该 ROB entry 对应的指令是否已执行完成。当某条指令执行结束时,会将 finish 对应的位置1,表示该指令已完成执行。               
    reg [`ROB_NUM-1:0] finish;
                 
    reg [`ROB_NUM-1:0] storebit;
    reg [`ROB_NUM-1:0] dstValid;
    reg [`ROB_NUM-1:0] brcond;
    reg [`ROB_NUM-1:0] isbranch;
    
    reg [`ADDR_LEN-1:0] inst_pc [0:`ROB_NUM-1];
    reg [`ADDR_LEN-1:0] jmpaddr [0:`ROB_NUM-1];    
    reg [`REG_SEL-1:0] dst [0:`ROB_NUM-1];
    reg [`GSH_BHR_LEN-1:0] bhr [0:`ROB_NUM-1];
    


    assign commit_ptr_2_o = (commit_ptr_1_o + 1) % (`ROB_NUM);

    wire commit_1 = valid[commit_ptr_1_o] & finish[commit_ptr_1_o] & ~prmiss_i;
    wire commit_2 = valid[commit_ptr_2_o] & finish[commit_ptr_2_o] & ~prmiss_i;

    assign comnum_o = commit_1 + commit_2;
    assign store_commit_o = (commit_1 & storebit[commit_ptr_1_o] & ~prmiss_i) | (commit_2 & storebit[commit_ptr_2_o] & ~prmiss_i);
    
    //提交到arf的目的逻辑寄存器地址
    assign dst_arf_1_o = dst[commit_ptr_1_o];
    assign dst_arf_2_o = dst[commit_ptr_2_o];


    assign arfwe_1_o =  ~prmiss_i & dstValid[commit_ptr_1_o] & commit_1;
    assign arfwe_2_o =  ~prmiss_i & dstValid[commit_ptr_2_o] & commit_2;


    // 收到prmiss信号时清空valid位
    always @(posedge clk) begin
        if (prmiss_i) begin
            valid[dispatch_ptr_i:commit_ptr_1_o] <= 0;
            commit_ptr_1_o <= dispatch_ptr_i; 
        end
    end


    always @(posedge clk ) begin
        if(reset) begin
            commit_ptr_1_o <= 0;
            valid <= 0;
            finish <= 0;
            brcond <= 0;
        end
        else begin
            commit_ptr_1_o <= (commit_ptr_1_o + commit_1 + commit_2) % (`ROB_NUM);
            if(finish_ex_alu1_i) begin
                finish[ex_alu1_addr_i] <= 1'b1;
            end             
            if(finish_ex_alu2_i) begin
                finish[finish_ex_alu2_addr_i] <= 1'b1;
            end
            if(finish_ex_branch_i) begin
                finish[finish_ex_branch_addr_i] <= 1'b1;
                //标记该条指令是否是条件分支指令
                brcond[finish_ex_branch_addr_i] <= finish_ex_branch_brcond_i;
                //记录分支指令的跳转地址
                jmpaddr[finish_ex_branch_addr_i] <= finish_ex_branch_jmpaddr_i;

            end
            if(finish_ex_mul_i) begin
                finish[finish_ex_mul_addr_i] <= 1'b1;
            end
            if(finish_ex_ldst_i)begin
                finish[finish_ex_ldst_addr_i] <= 1'b1;
            end
    
            // 当ROB entry的指令提交时,将valid置0
            if (commit_1) begin
                valid[commit_ptr_1_o] <= 1'b0; 
            end
            if (commit_2) begin
                valid[commit_ptr_2_o] <= 1'b0;
            end
        end
    end

    always @(posedge clk ) begin
        if(dp1_i) begin
            // 分配ROB entry
            valid[dp1_addr_i] <= 1'b1;
            //标记该条指令还未执行完成
            finish[dp1_addr_i] <= 1'b0;
            // 记录指令信息
            inst_pc[dp1_addr_i] <= pc_dp1_i;
            // 记录指令的目的寄存器
            dst[dp1_addr_i] <= dst_dp1_i;
            // 标记是否为分支指令
            isbranch[dp1_addr_i] <= isbranch_dp1_i;
            // 标记是否为存储类指令
            storebit[dp1_addr_i] <= storebit_dp1_i;
            // 标记目的寄存器是否有效
            dstValid[dp1_addr_i] <= dstvalid_dp1_i;
            // 记录分支指令的跳转地址
            bhr[dp1_addr_i] <= bhr_dp1_i;
        end
        if(dp2_i) begin
            // 分配ROB entry
            valid[dp2_addr_i] <= 1'b1;
            //标记该条指令还未执行完成
            finish[dp2_addr_i] <= 1'b0;
            // 记录指令信息
            inst_pc[dp2_addr_i] <= pc_dp2_i;
            // 记录指令的目的寄存器
            dst[dp2_addr_i] <= dst_dp2_i;
            // 标记是否为分支指令
            isbranch[dp2_addr_i] <= isbranch_dp2_i;
            // 标记是否为存储类指令
            storebit[dp2_addr_i] <= storebit_dp2_i;
            // 标记目的寄存器是否有效
            dstValid[dp2_addr_i] <= dstvalid_dp2_i;
            // 记录分支指令的跳转地址
            bhr[dp2_addr_i] <= bhr_dp2_i;
        end
    end



endmodule

testbench/COM/ROB_tb.v
`timescale 1ns / 1ps
`include "../../rtl/consts/Consts.v"
module ROB_tb();
    reg clk;
    reg reset;
    reg 			  dp1_i;                                     //是否发射
    reg [`RRF_SEL-1:0] 	  dp1_addr_i;                        //第一条发射的指令在ROB的地址
    reg [`INSN_LEN-1:0] 	  pc_dp1_i;
    reg 			  storebit_dp1_i;
    reg 			  dstvalid_dp1_i;
    reg [`REG_SEL-1:0] 	  dst_dp1_i;
    reg [`GSH_BHR_LEN-1:0]  bhr_dp1_i;
    reg 			  isbranch_dp1_i;
    reg 			  dp2_i;
    reg [`RRF_SEL-1:0] 	  dp2_addr_i;
    reg [`INSN_LEN-1:0] 	  pc_dp2_i;
    reg 			  storebit_dp2_i;
    reg 			  dstvalid_dp2_i;
    reg [`REG_SEL-1:0] 	  dst_dp2_i;
    reg [`GSH_BHR_LEN-1:0]  bhr_dp2_i;
    reg 			  isbranch_dp2_i;
    reg               finish_ex_alu1_i;                                    //alu1单元是否执行完成
    reg [`RRF_SEL-1:0] finish_ex_alu1_addr_i;                              //alu1执行完成的指令在ROB的地址
    reg 			  finish_ex_alu2_i;
    reg [`RRF_SEL-1:0] 	  finish_ex_alu2_addr_i;
    reg 			  finish_ex_mul_i;
    reg [`RRF_SEL-1:0] 	  finish_ex_mul_addr_i;
    reg 			  finish_ex_ldst_i;
    reg [`RRF_SEL-1:0] 	  finish_ex_ldst_addr_i;
    reg 			  finish_ex_branch_i;
    reg [`RRF_SEL-1:0] 	  finish_ex_branch_addr_i;
    reg 			  finish_ex_branch_brcond_i;
    reg [`ADDR_LEN-1:0]   finish_ex_branch_jmpaddr_i;
    reg [`RRF_SEL-1:0] dispatch_ptr_i;
    reg [`RRF_SEL-1:0] rrf_freenum_i;
    // reg prmiss_i;

    wire [`ROB_SEL-1:0] commit_ptr_1_o;
    wire [`ROB_SEL-1:0] commit_ptr_2_o;
    wire [1:0] comnum_o;
    wire store_commit_o;
    wire arfwe_1_o;
    wire arfwe_2_o;
    wire [`REG_SEL-1:0] dst_arf_1_o;
    wire [`REG_SEL-1:0] dst_arf_2_o;
    wire [`ADDR_LEN-1:0] pc_combranch_o;
    wire [`GSH_BHR_LEN-1:0] bhr_combranch_o;
    wire [`ADDR_LEN-1:0] jmpaddr_combranch_o;
    wire brcond_combranch_o;
    wire combranch_o;

    // 实例化ROB
    ROB dut (
        .clk(clk),
        .reset(reset),
        .dp1_i(dp1_i),
        .dp1_addr_i(dp1_addr_i),
        .pc_dp1_i(pc_dp1_i),
        .storebit_dp1_i(storebit_dp1_i),
        .dstvalid_dp1_i(dstvalid_dp1_i),
        .dst_dp1_i(dst_dp1_i),
        .bhr_dp1_i(bhr_dp1_i),
        .isbranch_dp1_i(isbranch_dp1_i),
        .dp2_i(dp2_i),
        .dp2_addr_i(dp2_addr_i),
        .pc_dp2_i(pc_dp2_i),
        .storebit_dp2_i(storebit_dp2_i),
        .dstvalid_dp2_i(dstvalid_dp2_i),
        .dst_dp2_i(dst_dp2_i),
        .bhr_dp2_i(bhr_dp2_i),
        .isbranch_dp2_i(isbranch_dp2_i),
        .finish_ex_alu1_i(finish_ex_alu1_i),
        .finish_ex_alu1_addr_i(finish_ex_alu1_addr_i),
        .finish_ex_alu2_i(finish_ex_alu2_i),
        .finish_ex_alu2_addr_i(finish_ex_alu2_addr_i),
        .finish_ex_mul_i(finish_ex_mul_i),
        .finish_ex_mul_addr_i(finish_ex_mul_addr_i),
        .finish_ex_ldst_i(finish_ex_ldst_i),
        .finish_ex_ldst_addr_i(finish_ex_ldst_addr_i),
        .finish_ex_branch_i(finish_ex_branch_i),
        .finish_ex_branch_addr_i(finish_ex_branch_addr_i),
        .finish_ex_branch_brcond_i(finish_ex_branch_brcond_i),
        .finish_ex_branch_jmpaddr_i(finish_ex_branch_jmpaddr_i),
        .dispatch_ptr_i(dispatch_ptr_i),
        .rrf_freenum_i(rrf_freenum_i),
        // .prmiss_i(prmiss_i),

        .commit_ptr_1_o(commit_ptr_1_o),
        .commit_ptr_2_o(commit_ptr_2_o),
        .comnum_o(comnum_o),
        .store_commit_o(store_commit_o),
        .arfwe_1_o(arfwe_1_o),
        .arfwe_2_o(arfwe_2_o),
        .dst_arf_1_o(dst_arf_1_o),
        .dst_arf_2_o(dst_arf_2_o),
        .pc_combranch_o(pc_combranch_o),
        .bhr_combranch_o(bhr_combranch_o),
        .jmpaddr_combranch_o(jmpaddr_combranch_o),
        .brcond_combranch_o(brcond_combranch_o),
        .combranch_o(combranch_o)
    );

    initial begin
        clk = 0;
        forever #5 clk = ~clk;
    end

    initial begin
                $dumpfile("ROB_tb.vcd");    //生成的vcd文件名称
                $dumpvars(0, ROB_tb);       //要记录的信号  0代表所有
            end
 
    initial begin
        reset = 1;
        dp1_i = 0;
        dp1_addr_i = 0;
        pc_dp1_i = 0;
        storebit_dp1_i = 0;
        dstvalid_dp1_i = 0;
        dst_dp1_i = 0;
        bhr_dp1_i = 0;
        isbranch_dp1_i = 0;

        dp2_i = 0;
        dp2_addr_i = 0;
        pc_dp2_i = 0;
        storebit_dp1_i = 0;
        dstvalid_dp2_i = 0;
        dst_dp2_i = 0;
        bhr_dp2_i = 0;
        isbranch_dp2_i = 0;


        #10 reset = 0; 


        #20 dp1_i = 1;
            dp1_addr_i = 0;
            dst_dp1_i[dp1_addr_i] = 1;                

        #5 finish_ex_alu1_i = 1;
            finish_ex_alu1_addr_i = dp1_addr_i;


        #100 $stop;
        $finish();
    end

endmodule

testbench/COM/ROB_tb.vcd
$date
	Wed Dec  6 19:49:29 2023
$end
$version
	Icarus Verilog
$end
$timescale
	1ps
$end
$scope module ROB_tb $end
$var wire 1 ! brcond_combranch_o $end
$var wire 1 " store_commit_o $end
$var wire 32 # pc_combranch_o [31:0] $end
$var wire 32 $ jmpaddr_combranch_o [31:0] $end
$var wire 5 % dst_arf_2_o [4:0] $end
$var wire 5 & dst_arf_1_o [4:0] $end
$var wire 2 ' comnum_o [1:0] $end
$var wire 6 ( commit_ptr_2_o [5:0] $end
$var wire 6 ) commit_ptr_1_o [5:0] $end
$var wire 1 * combranch_o $end
$var wire 10 + bhr_combranch_o [9:0] $end
$var wire 1 , arfwe_2_o $end
$var wire 1 - arfwe_1_o $end
$var reg 10 . bhr_dp1_i [9:0] $end
$var reg 10 / bhr_dp2_i [9:0] $end
$var reg 1 0 clk $end
$var reg 6 1 dispatch_ptr_i [5:0] $end
$var reg 6 2 dp1_addr_i [5:0] $end
$var reg 1 3 dp1_i $end
$var reg 6 4 dp2_addr_i [5:0] $end
$var reg 1 5 dp2_i $end
$var reg 5 6 dst_dp1_i [4:0] $end
$var reg 5 7 dst_dp2_i [4:0] $end
$var reg 1 8 dstvalid_dp1_i $end
$var reg 1 9 dstvalid_dp2_i $end
$var reg 6 : finish_ex_alu1_addr_i [5:0] $end
$var reg 1 ; finish_ex_alu1_i $end
$var reg 6 < finish_ex_alu2_addr_i [5:0] $end
$var reg 1 = finish_ex_alu2_i $end
$var reg 6 > finish_ex_branch_addr_i [5:0] $end
$var reg 1 ? finish_ex_branch_brcond_i $end
$var reg 1 @ finish_ex_branch_i $end
$var reg 32 A finish_ex_branch_jmpaddr_i [31:0] $end
$var reg 6 B finish_ex_ldst_addr_i [5:0] $end
$var reg 1 C finish_ex_ldst_i $end
$var reg 6 D finish_ex_mul_addr_i [5:0] $end
$var reg 1 E finish_ex_mul_i $end
$var reg 1 F isbranch_dp1_i $end
$var reg 1 G isbranch_dp2_i $end
$var reg 32 H pc_dp1_i [31:0] $end
$var reg 32 I pc_dp2_i [31:0] $end
$var reg 1 J reset $end
$var reg 6 K rrf_freenum_i [5:0] $end
$var reg 1 L storebit_dp1_i $end
$var reg 1 M storebit_dp2_i $end
$scope module dut $end
$var wire 1 - arfwe_1_o $end
$var wire 1 , arfwe_2_o $end
$var wire 10 N bhr_dp1_i [9:0] $end
$var wire 10 O bhr_dp2_i [9:0] $end
$var wire 1 ! brcond_combranch_o $end
$var wire 1 0 clk $end
$var wire 1 * combranch_o $end
$var wire 1 P commit_1 $end
$var wire 1 Q commit_2 $end
$var wire 6 R dispatch_ptr_i [5:0] $end
$var wire 6 S dp1_addr_i [5:0] $end
$var wire 1 3 dp1_i $end
$var wire 6 T dp2_addr_i [5:0] $end
$var wire 1 5 dp2_i $end
$var wire 5 U dst_arf_1_o [4:0] $end
$var wire 5 V dst_arf_2_o [4:0] $end
$var wire 5 W dst_dp1_i [4:0] $end
$var wire 5 X dst_dp2_i [4:0] $end
$var wire 1 8 dstvalid_dp1_i $end
$var wire 1 9 dstvalid_dp2_i $end
$var wire 6 Y finish_ex_alu1_addr_i [5:0] $end
$var wire 1 ; finish_ex_alu1_i $end
$var wire 6 Z finish_ex_alu2_addr_i [5:0] $end
$var wire 1 = finish_ex_alu2_i $end
$var wire 6 [ finish_ex_branch_addr_i [5:0] $end
$var wire 1 ? finish_ex_branch_brcond_i $end
$var wire 1 @ finish_ex_branch_i $end
$var wire 32 \ finish_ex_branch_jmpaddr_i [31:0] $end
$var wire 6 ] finish_ex_ldst_addr_i [5:0] $end
$var wire 1 C finish_ex_ldst_i $end
$var wire 6 ^ finish_ex_mul_addr_i [5:0] $end
$var wire 1 E finish_ex_mul_i $end
$var wire 1 F isbranch_dp1_i $end
$var wire 1 G isbranch_dp2_i $end
$var wire 32 _ pc_dp1_i [31:0] $end
$var wire 32 ` pc_dp2_i [31:0] $end
$var wire 1 a prmiss_i $end
$var wire 1 J reset $end
$var wire 6 b rrf_freenum_i [5:0] $end
$var wire 1 " store_commit_o $end
$var wire 1 L storebit_dp1_i $end
$var wire 1 M storebit_dp2_i $end
$var wire 32 c pc_combranch_o [31:0] $end
$var wire 32 d jmpaddr_combranch_o [31:0] $end
$var wire 2 e comnum_o [1:0] $end
$var wire 6 f commit_ptr_2_o [5:0] $end
$var wire 10 g bhr_combranch_o [9:0] $end
$var reg 64 h brcond [63:0] $end
$var reg 6 i commit_ptr_1_o [5:0] $end
$var reg 64 j dstValid [63:0] $end
$var reg 64 k finish [63:0] $end
$var reg 64 l isbranch [63:0] $end
$var reg 64 m storebit [63:0] $end
$var reg 64 n valid [63:0] $end
$upscope $end
$upscope $end
$enddefinitions $end
$comment Show the parameter values. $end
$dumpall
$end
#0
$dumpvars
bx n
bx m
bx l
bx k
bx j
bx i
bx h
bx g
bx f
bx e
bx d
bx c
bx b
za
b0 `
b0 _
bx ^
bx ]
bx \
bx [
bx Z
bx Y
b0 X
b0 W
bx V
bx U
b0 T
b0 S
bx R
xQ
xP
b0 O
b0 N
xM
0L
bx K
1J
b0 I
b0 H
0G
0F
xE
bx D
xC
bx B
bx A
x@
x?
bx >
x=
bx <
x;
bx :
09
08
b0 7
b0 6
05
b0 4
03
b0 2
bx 1
00
b0 /
b0 .
x-
x,
bx +
x*
bx )
bx (
bx '
bx &
bx %
bx $
bx #
x"
z!
$end
#5000
0*
0"
0,
0-
b0 '
b0 e
0Q
0P
b1 (
b1 f
b0 h
b0 k
b0 n
b0 )
b0 i
10
#10000
00
0J
#15000
10
#20000
00
#25000
10
#30000
00
b1 6
b1 W
13
#35000
bx0 j
bx0 m
bx0 l
b1 &
b1 U
b1 n
b0 k
10
b0 :
b0 Y
1;
#40000
00
#45000
b1 '
b1 e
1P
b1 k
10
#50000
00
#55000
0"
0*
b10 (
b10 f
b0 '
b0 e
0P
0-
b0 k
b1 n
bx &
bx U
b1 )
b1 i
10
#60000
00
#65000
b1 k
10
#70000
00
#75000
b0 k
10
#80000
00
#85000
b1 k
10
#90000
00
#95000
b0 k
10
#100000
00
#105000
b1 k
10
#110000
00
#115000
b0 k
10
#120000
00
#125000
b1 k
10
